[
    {
        "tnr": "151554",
        "Antall": 50,
        "Tittelnr": "0151554",
        "Tittel": "Guinness world records 2019",
        "Originaltittel": " Guinness World Records 2019 ",
        "Medvirkende": "Sand, Tore (redakt\u00f8r)",
        "Spr\u00e5k": "bokm\u00e5l",
        "Utgitt": " Bergen  : Vigmostad Bj\u00f8rke , 2018",
        "Omfang": "255 s. : kol. ill.",
        "Passer for": "fra 9 \u00e5r",
        "Opplysninger": "1. norske utg.: Oslo : Schibsted, 1967 med tittel: F\u00f8rst og st\u00f8rst, sist og minst, Originaltittel: Guinness World Records 2019, Har register, Alder: 9-16 \u00e5r",
        "Emner": "Rekorder, Oppslagsb\u00f8ker",
        "Sjanger": "Oppslagsbok",
        "Dewey": "032.02",
        "ISBN": "978-82-419-1738-7 (ib.) : Nkr 339.00",
        "Hylleplass": "030",
        "bibliofilid": 11432251,
        "copies": "https:\/\/ullensaker.bib.no\/cgi-bin\/rest_service\/copies\/1.0\/data\/151554?fields=full&exfields=full",
        "Krydderbilde": "https:\/\/krydder.bib.no\/1089\/11432251.bilde.1667572234.k.jpg",
        "Krydderbeskrivelse": "Boka inneholder oppdaterte og spektakul\u00e6re rekorder av alle slag: fra naturens verden, menneskeheten, vitenskap og teknologi, byggverk, transport, kultur, underholdning, idrett og fra menneskers meritter. Rekordene er samlet under ulike overskrifter p\u00e5 dobbeltsideoppslag. F\u00f8rst i boken st\u00e5r informasjon om hvordan man kan sette rekorder selv. Boka inneholder ogs\u00e5 intervjuer med rekordholdere. \u00c5rets spesielle nyhet er \u00abMeet the Makers\u00bb og \u00abMaking History\u00bb -kapitlene, som kreativit viser hvordan man kan bygge ting hjemme p\u00e5 egen h\u00e5nd. Alle som \u00f8nsker \u00e5 sette en rekord hjemme, vil finne inspirasjon i \u00abGj\u00f8r dette hjemme\u00bb-seksjonen. Sakprosa for mellom-\/ungdomstrinnet. Omtalen er utarbeidet av BS.\n"
    },
    {
        "tnr": "116085",
        "Antall": 42,
        "Tittelnr": "0116085",
        "Tittel": "Minecraft : redstone-h\u00e5ndboka",
        "Originaltittel": " Minecraft redstone handbook ",
        "Forfatter": "Farwell, Nick",
        "Medvirkende": "Burlinson, James (illustrat\u00f8r), R\u00f8s\u00e5sen, Jens Erik (oversetter)",
        "Spr\u00e5k": "bokm\u00e5l",
        "Utgitt": "Oslo : Egmont Kids Media , 2015",
        "Omfang": "95 s. : kol. ill.",
        "Passer for": "fra 9 \u00e5r",
        "Opplysninger": "Originaltittel: Minecraft redstone handbook, Alder: 9-16 \u00e5r",
        "Emner": "Minecraft(dataspill)",
        "Dewey": "794.8",
        "ISBN": "978-82-429-5302-5 (ib.) : Nkr 129.00",
        "Hylleplass": "794.8",
        "bibliofilid": 10379748,
        "copies": "https:\/\/ullensaker.bib.no\/cgi-bin\/rest_service\/copies\/1.0\/data\/116085?fields=full&exfields=full",
        "Krydderbilde": "https:\/\/krydder.bib.no\/0950\/10379748.bilde.1667579725.k.jpg"
    },
    {
        "tnr": "125377",
        "Antall": 39,
        "Tittelnr": "0125377",
        "Tittel": "Sommerkviss",
        "Originaltittel": " For hele familien ",
        "Spr\u00e5k": "bokm\u00e5l",
        "Utgitt": " Oslo  : Victoria , cop. 2016",
        "Omfang": "250 s.",
        "Passer for": "fra 9 \u00e5r",
        "Opplysninger": "Undertitel p\u00e5 omslaget: For hele familien, Alder: 9-16 \u00e5r, God, leselig skrift",
        "Emner": "Sp\u00f8rreb\u00f8ker, Leker og aktiviteter",
        "Dewey": "793.73",
        "ISBN": "978-82-93251-75-0 (ib.) : Nkr 79.00",
        "Hylleplass": "793.7",
        "bibliofilid": 10518709,
        "copies": "https:\/\/ullensaker.bib.no\/cgi-bin\/rest_service\/copies\/1.0\/data\/125377?fields=full&exfields=full",
        "Krydderbilde": "https:\/\/krydder.bib.no\/0974\/10518709.bilde.1667583451.k.jpg"
    },
    {
        "tnr": "138418",
        "Antall": 39,
        "Tittelnr": "0138418",
        "Tittel": "Detektivh\u00e5ndbok",
        "Forfatter": "Horst, J\u00f8rn Lier  1970-",
        "Medvirkende": "Sandnes, Hans J\u00f8rgen (illustrat\u00f8r)",
        "Spr\u00e5k": "bokm\u00e5l",
        "Utgitt": "Oslo : Gyldendal , 2017",
        "Omfang": "114 s. : kol. ill.",
        "Passer for": "fra 6 til 10 \u00e5r",
        "Opplysninger": "Alder: 6-11 \u00e5r",
        "Emner": "Detektivleker, Leker og aktiviteter",
        "Dewey": "793",
        "ISBN": "978-82-05-50707-4 (ib.) : Nkr 279.00, 978-82-525-8824-8 (Bokklubben)",
        "Hylleplass": "790",
        "bibliofilid": 10811309,
        "copies": "https:\/\/ullensaker.bib.no\/cgi-bin\/rest_service\/copies\/1.0\/data\/138418?fields=full&exfields=full",
        "Krydderbilde": "https:\/\/krydder.bib.no\/1032\/10811309.bilde.1667575844.k.jpg",
        "Krydderbeskrivelse": "Her kan man l\u00e6re \u00e5 bli en god detektiv sammen med Tiril, Olivier og hunden \u00c5tto i Detektivbyr\u00e5 nr. 2. I boka f\u00e5r man tips og r\u00e5d til hvordan bli en god detektiv, hva det f\u00f8rste man m\u00e5 gj\u00f8re n\u00e5r man skal l\u00f8se et mysterium, hvordan man leter etter spor, eller hvordan man tar fingeravtrykk. For sm\u00e5skole-\/mellomtrinnet. Omtalen er utarbeidet av BS.\n"
    },
    {
        "tnr": "116084",
        "Antall": 36,
        "Tittelnr": "0116084",
        "Tittel": "Minecraft : h\u00e5ndbok for nybegynnere",
        "Originaltittel": " Minecraft beginners handbook ",
        "Forfatter": "Milton, Stephanie",
        "Medvirkende": "Maron, Jordan (medforfatter), Soares, Paul (medforfatter), Burlinson, James (illustrat\u00f8r), R\u00f8s\u00e5sen, Jens Erik (oversetter)",
        "Spr\u00e5k": "bokm\u00e5l",
        "Utgitt": "Oslo : Egmont Kids Media , 2015",
        "Omfang": "95 s. : kol. ill.",
        "Passer for": "fra 9 \u00e5r",
        "Opplysninger": "Originaltittel: Minecraft beginners handbook, Alder: 9-16 \u00e5r",
        "Emner": "Minecraft(dataspill)",
        "Dewey": "794.8",
        "ISBN": "978-82-429-5301-8 (ib.) : Nkr 129.00",
        "Hylleplass": "794.8",
        "bibliofilid": 10377819,
        "copies": "https:\/\/ullensaker.bib.no\/cgi-bin\/rest_service\/copies\/1.0\/data\/116084?fields=full&exfields=full",
        "Krydderbilde": "https:\/\/krydder.bib.no\/0950\/10377819.bilde.1441631498.k.jpg",
        "Krydderbeskrivelse": "Med denne offisielle nybegynnerh\u00e5ndboka for Minecraft f\u00e5r man r\u00e5d og tips til hvordan man faktisk kan redde livet i denne mystiske spillverdenen fylt med skjulte farer. H\u00e5ndboka l\u00e6rer spilleren \u00e5 finne ressurser, bygge hus, lage verkt\u00f8y, rustninger og v\u00e5pen, samt beskytte seg mot monstre. Med tips fra Minecraft-eksperter, fra utvikleren Jeb og fra selveste skaperen Notch er dette den definitive guide for \u00e5 overleve de f\u00f8rste dagene i Minecraft. Sakprosa for mellomtrinnet.\n"
    },
    {
        "tnr": "147935",
        "Antall": 33,
        "Tittelnr": "0147935",
        "Tittel": "Alt du trenger \u00e5 vite om hunder og valper : l\u00e6r om stell av hunder og valper",
        "Medvirkende": "Myhra, Per (redakt\u00f8r), Thuesen, Nils Petter (oversetter)",
        "Spr\u00e5k": "bokm\u00e5l",
        "Utgitt": "Oslo : Norsk fakta forl. , 2016",
        "Omfang": "45 s. : kol. ill.",
        "Passer for": "fra 6 til 12 \u00e5r",
        "Opplysninger": "Katalogisert etter omslaget, Har ordliste, register, Alder: 6-13 \u00e5r",
        "Emner": "Hunder, Dyr",
        "Dewey": "636.7",
        "ISBN": "978-82-7888-465-2 (ib.) : Nkr 99.00",
        "Hylleplass": "636.7",
        "bibliofilid": 10573019,
        "copies": "https:\/\/ullensaker.bib.no\/cgi-bin\/rest_service\/copies\/1.0\/data\/147935?fields=full&exfields=full",
        "Krydderbilde": "https:\/\/krydder.bib.no\/0990\/10573019.bilde.1667574397.k.jpg",
        "Krydderbeskrivelse": "\u00c5 ta vare p\u00e5 hunder og valper er skrevet i et barnevennlig spr\u00e5k og er en utmerket referanse bok for barna. Boken hjelper barna til \u00e5 ta vare p\u00e5 hunder og valper p\u00e5 en forsvarlig m\u00e5te og mest mulig p\u00e5 egen h\u00e5nd. Teksten er ledsaget av flotte fotografier og fargerike illustrasjoner og er en skattekiste av informasjon om hundetyper og valper samt deres helse og atferd. Boken fungerer ogs\u00e5 som guide til kj\u00f8p av hund eller valp.\n"
    },
    {
        "tnr": "116086",
        "Antall": 32,
        "Tittelnr": "0116086",
        "Tittel": "Minecraft : kamph\u00e5ndboka",
        "Originaltittel": " Minecraft ",
        "Forfatter": "Milton, Stephanie",
        "Medvirkende": "Bolder, Joe (illustrat\u00f8r), Cordner, Theo (illustrat\u00f8r), R\u00f8s\u00e5sen, Jens Erik (oversetter), Soares, Paul (medforfatter)",
        "Spr\u00e5k": "bokm\u00e5l",
        "Utgitt": "Oslo : Egmont Kids Media , 2015",
        "Omfang": "95 s. : kol. ill.",
        "Passer for": "fra 9 \u00e5r",
        "Opplysninger": "Originaltittel: Minecraft, Alder: 9-16 \u00e5r",
        "Emner": "Minecraft(dataspill)",
        "Dewey": "794.8",
        "ISBN": "978-82-429-5303-2 (ib.) : Nkr 129.00",
        "Hylleplass": "794.8",
        "bibliofilid": 10375582,
        "copies": "https:\/\/ullensaker.bib.no\/cgi-bin\/rest_service\/copies\/1.0\/data\/116086?fields=full&exfields=full",
        "Krydderbilde": "https:\/\/krydder.bib.no\/0950\/10375582.bilde.1667578777.k.jpg",
        "Krydderbeskrivelse": "I Minecraft er du aldri alene. Hele tiden st\u00e5r du i fare for \u00e5 bli angrepet. Hvordan skal du klare \u00e5 overleve?<br>\nDen offisielle kamph\u00e5ndboka l\u00e6rer deg alt du trenger \u00e5 vite om \u00e5 forsvare deg mot monstre og fiendtlige spillere.<p>\nL\u00e6r \u00e5 bygge en festning, lage rustninger og v\u00e5pen, legge feller, beseire fiender i tvekamp og kjempe de ut av Nether og End. Med tips fra mange Minecraft-kriger p\u00e5 rekordtid.\n"
    },
    {
        "tnr": "155031",
        "Antall": 32,
        "Tittelnr": "0155031",
        "Tittel": "D\u00f8delige dinosaurer",
        "Originaltittel": " Deadly dinosaurs ",
        "Forfatter": "Llewellyn, Claire",
        "Medvirkende": "Feldman, Thea (medforfatter), N\u00e6ss, Jan Christopher (oversetter)",
        "Spr\u00e5k": "bokm\u00e5l",
        "Utgitt": "Oslo : Gyldendal , 2019",
        "Omfang": "32 s. : kol. ill.",
        "Passer for": "fra 6 til 10 \u00e5r",
        "Opplysninger": "Originaltittel: Deadly dinosaurs, Har ordliste, register, Alder: 6-11 \u00e5r, Lettlest",
        "Emner": "Dinosaurer, Lettlest 3",
        "Dewey": "567.9",
        "ISBN": "978-82-05-51572-7 (ib.) : Nkr 169.00",
        "bibliofilid": 11810632,
        "copies": "https:\/\/ullensaker.bib.no\/cgi-bin\/rest_service\/copies\/1.0\/data\/155031?fields=full&exfields=full",
        "Krydderbilde": "https:\/\/krydder.bib.no\/1425\/11810271.bilde.1667571362.k.jpg",
        "Krydderbeskrivelse": "Her kan man lese om store kjemper, n\u00e5del\u00f8se drapsmaskiner, grusomme kl\u00f8r og flygende \u00f8gler. Finne ut hvilken dinosaur om var den r\u00e5este drapsmaskinen eller hvor lang tanna til tyrannosaurus rex var. I tillegg inneholder boka fakta, statistikker, hvem som er hvem blant dinosaurene, hvordan dinosaurforskerne jobber og mye mer. \u00abLes mer om \u2026\u00bb inng\u00e5r i en serie lettlest faktab\u00f8ker, med korte kapitler og mange fotografier. Teksten er lett tilgjengelig og delvis ordnet i undergrupper som bildetekst, fakta eller skilt ut grafisk. Bakerst er et register hvor vanskelige ord blir forklart. Sakprosa for sm\u00e5skole-\/mellomtrinnet. Omtalen er utarbeidet av BS.\n"
    },
    {
        "tnr": "147936",
        "Antall": 31,
        "Tittelnr": "0147936",
        "Tittel": "Alt du trenger \u00e5 vite om katter og kattunger : l\u00e6r om stell av katter og kattunger",
        "Originaltittel": " Caring for cats and kittens ",
        "Medvirkende": "Myhra, Per (redakt\u00f8r), Thuesen, Nils Petter (oversetter)",
        "Spr\u00e5k": "bokm\u00e5l",
        "Utgitt": " Oslo  : Norsk fakta forl. , 2016",
        "Omfang": "45 s. : kol. ill.",
        "Passer for": "fra 6 til 12 \u00e5r",
        "Opplysninger": "Katalogisert etter omslaget, Originaltittel: Caring for cats and kittens, Har ordliste, register, Alder: 6-13 \u00e5r",
        "Emner": "Katter, Dyr",
        "Dewey": "636.8",
        "ISBN": "978-82-7888-466-9 (ib.) : Nkr 99.00",
        "Hylleplass": "636.8",
        "bibliofilid": 10571576,
        "copies": "https:\/\/ullensaker.bib.no\/cgi-bin\/rest_service\/copies\/1.0\/data\/147936?fields=full&exfields=full",
        "Krydderbilde": "https:\/\/krydder.bib.no\/0991\/10571576.bilde.1667587769.k.jpg",
        "Krydderbeskrivelse": "Skrevet som den er i et barnevennlig spr\u00e5k, er \"Alt du trenger \u00e5 vite om katter og kattunger\" en utmerket referanse bok for barna, og er laget for \u00e5 hjelpe barn til \u00e5 ta vare p\u00e5 katter og kattunger p\u00e5 en s\u00e5 ansvarlig og uavhengig m\u00e5te som mulig. Med flotte fotografier og fargerike illustrasjoner i tillegg til teksten er denne boken en skattekiste av informasjon om raser av katter og kattunger samt deres helse og atferd. Boken fungerer ogs\u00e5 som en guide til kj\u00f8p av katt eller kattunge.\n"
    },
    {
        "tnr": "154285",
        "Antall": 31,
        "Tittelnr": "0154285",
        "Tittel": "Hai!",
        "Forfatter": "R\u00f8ed, Henning  1955-",
        "Spr\u00e5k": "bokm\u00e5l",
        "Utgitt": " Oslo  : Cappelen Damm , 2019",
        "Omfang": " 29  s. : kol.ill.",
        "Passer for": "fra 3 til 8 \u00e5r",
        "Opplysninger": "Alder: 3-9 \u00e5r, Lettlest",
        "Emner": "Haier, Lettlest 1",
        "Dewey": "597.3",
        "ISBN": "978-82-02-61706-6 (ib.) : Nkr 169.00",
        "bibliofilid": 11546037,
        "copies": "https:\/\/ullensaker.bib.no\/cgi-bin\/rest_service\/copies\/1.0\/data\/154285?fields=full&exfields=full",
        "Krydderbilde": "https:\/\/krydder.bib.no\/1440\/11546037.bilde.1667571803.k.jpg",
        "Krydderbeskrivelse": "Hvem er den skumleste jegeren i havet? 10 av 10 ganger vil barn svare haien. Her kommer boka om beistet med de skarpe tennene, tilrettelagt for 4 til 7-\u00e5ringen. Visste du at haier kan lukte blod? Eller at de trenger hjelp til \u00e5 pusse tennene? Eller at Norges minste hai har egne lykter p\u00e5 magen? Haien er en av naturens mest fascinerende vesener, og de har eksistert siden f\u00f8r dinosaurene. L\u00f8veunge - Sm\u00e5 og fargerike bildeb\u00f8ker, fortalt med lite tekst. Det er kun \u00e9n setning p\u00e5 hver side. L\u00f8veungene er perfekte b\u00f8ker for de aller ferskeste leserne.\n"
    }
]